odoo10_addon_sms_send_picking-10.0.1.0.0.99.dev8-py2.7-nspkg.pth
odoo/addons/sms_send_picking/README.rst
odoo/addons/sms_send_picking/__init__.py
odoo/addons/sms_send_picking/__manifest__.py
odoo/addons/sms_send_picking/data/cron.xml
odoo/addons/sms_send_picking/i18n/es.po
odoo/addons/sms_send_picking/i18n/fr.po
odoo/addons/sms_send_picking/i18n/sms_send_picking.pot
odoo/addons/sms_send_picking/models/__init__.py
odoo/addons/sms_send_picking/models/stock.py
odoo/addons/sms_send_picking/static/description/icon.png
odoo/addons/sms_send_picking/tests/__init__.py
odoo/addons/sms_send_picking/tests/test_sms_send_picking.py
odoo10_addon_sms_send_picking-10.0.1.0.0.99.dev8.dist-info/METADATA
odoo10_addon_sms_send_picking-10.0.1.0.0.99.dev8.dist-info/RECORD
odoo10_addon_sms_send_picking-10.0.1.0.0.99.dev8.dist-info/WHEEL
odoo10_addon_sms_send_picking-10.0.1.0.0.99.dev8.dist-info/namespace_packages.txt
odoo10_addon_sms_send_picking-10.0.1.0.0.99.dev8.dist-info/top_level.txt
